[{"Name":"Logograms","TerritoryId":1,"Variants":[{"Id":24007,"Name":"Conceptual Logogram","Patches":{"7.1":{"Total":370805,"Items":[{"Id":24033,"Amount":52653,"Pct":0.141996,"Total":52653,"Min":1,"Max":1},{"Id":24024,"Amount":52689,"Pct":0.142094,"Total":52689,"Min":1,"Max":1},{"Id":24030,"Amount":52809,"Pct":0.142417,"Total":52809,"Min":1,"Max":1},{"Id":24016,"Amount":52919,"Pct":0.142714,"Total":52919,"Min":1,"Max":1},{"Id":24017,"Amount":53029,"Pct":0.14301,"Total":53029,"Min":1,"Max":1},{"Id":24037,"Amount":53298,"Pct":0.143736,"Total":53298,"Min":1,"Max":1},{"Id":24015,"Amount":53408,"Pct":0.144033,"Total":53408,"Min":1,"Max":1}]},"All":{"Total":370805,"Items":[{"Id":24033,"Amount":52653,"Pct":0.141996,"Total":52653,"Min":1,"Max":1},{"Id":24024,"Amount":52689,"Pct":0.142094,"Total":52689,"Min":1,"Max":1},{"Id":24030,"Amount":52809,"Pct":0.142417,"Total":52809,"Min":1,"Max":1},{"Id":24016,"Amount":52919,"Pct":0.142714,"Total":52919,"Min":1,"Max":1},{"Id":24017,"Amount":53029,"Pct":0.14301,"Total":53029,"Min":1,"Max":1},{"Id":24037,"Amount":53298,"Pct":0.143736,"Total":53298,"Min":1,"Max":1},{"Id":24015,"Amount":53408,"Pct":0.144033,"Total":53408,"Min":1,"Max":1}]}}},{"Id":24008,"Name":"Fundamental Logogram","Patches":{"7.1":{"Total":173373,"Items":[{"Id":24038,"Amount":34570,"Pct":0.199397,"Total":34570,"Min":1,"Max":1},{"Id":24028,"Amount":34571,"Pct":0.199402,"Total":34571,"Min":1,"Max":1},{"Id":24036,"Amount":34614,"Pct":0.19965,"Total":34614,"Min":1,"Max":1},{"Id":24031,"Amount":34718,"Pct":0.20025,"Total":34718,"Min":1,"Max":1},{"Id":24022,"Amount":34900,"Pct":0.2013,"Total":34900,"Min":1,"Max":1}]},"All":{"Total":173373,"Items":[{"Id":24038,"Amount":34570,"Pct":0.199397,"Total":34570,"Min":1,"Max":1},{"Id":24028,"Amount":34571,"Pct":0.199402,"Total":34571,"Min":1,"Max":1},{"Id":24036,"Amount":34614,"Pct":0.19965,"Total":34614,"Min":1,"Max":1},{"Id":24031,"Amount":34718,"Pct":0.20025,"Total":34718,"Min":1,"Max":1},{"Id":24022,"Amount":34900,"Pct":0.2013,"Total":34900,"Min":1,"Max":1}]}}},{"Id":24009,"Name":"Curative Logogram","Patches":{"7.1":{"Total":29805,"Items":[{"Id":24019,"Amount":14864,"Pct":0.498708,"Total":14864,"Min":1,"Max":1},{"Id":24034,"Amount":14941,"Pct":0.501292,"Total":14941,"Min":1,"Max":1}]},"All":{"Total":29805,"Items":[{"Id":24019,"Amount":14864,"Pct":0.498708,"Total":14864,"Min":1,"Max":1},{"Id":24034,"Amount":14941,"Pct":0.501292,"Total":14941,"Min":1,"Max":1}]}}},{"Id":24010,"Name":"Offensive Logogram","Patches":{"7.1":{"Total":58397,"Items":[{"Id":24032,"Amount":29066,"Pct":0.497731,"Total":29066,"Min":1,"Max":1},{"Id":24020,"Amount":29331,"Pct":0.502269,"Total":29331,"Min":1,"Max":1}]},"All":{"Total":58397,"Items":[{"Id":24032,"Amount":29066,"Pct":0.497731,"Total":29066,"Min":1,"Max":1},{"Id":24020,"Amount":29331,"Pct":0.502269,"Total":29331,"Min":1,"Max":1}]}}},{"Id":24011,"Name":"Protective Logogram","Patches":{"7.1":{"Total":9725,"Items":[{"Id":24018,"Amount":4857,"Pct":0.499434,"Total":4857,"Min":1,"Max":1},{"Id":24021,"Amount":4868,"Pct":0.500566,"Total":4868,"Min":1,"Max":1}]},"All":{"Total":9725,"Items":[{"Id":24018,"Amount":4857,"Pct":0.499434,"Total":4857,"Min":1,"Max":1},{"Id":24021,"Amount":4868,"Pct":0.500566,"Total":4868,"Min":1,"Max":1}]}}},{"Id":24012,"Name":"Tactical Logogram","Patches":{"7.1":{"Total":24327,"Items":[{"Id":24029,"Amount":12127,"Pct":0.4985,"Total":12127,"Min":1,"Max":1},{"Id":24025,"Amount":12200,"Pct":0.5015,"Total":12200,"Min":1,"Max":1}]},"All":{"Total":24327,"Items":[{"Id":24029,"Amount":12127,"Pct":0.4985,"Total":12127,"Min":1,"Max":1},{"Id":24025,"Amount":12200,"Pct":0.5015,"Total":12200,"Min":1,"Max":1}]}}},{"Id":24013,"Name":"Mitigative Logogram","Patches":{"7.1":{"Total":24421,"Items":[{"Id":24023,"Amount":12151,"Pct":0.497564,"Total":12151,"Min":1,"Max":1},{"Id":24035,"Amount":12270,"Pct":0.502436,"Total":12270,"Min":1,"Max":1}]},"All":{"Total":24421,"Items":[{"Id":24023,"Amount":12151,"Pct":0.497564,"Total":12151,"Min":1,"Max":1},{"Id":24035,"Amount":12270,"Pct":0.502436,"Total":12270,"Min":1,"Max":1}]}}},{"Id":24014,"Name":"Inimical Logogram","Patches":{"7.1":{"Total":33249,"Items":[{"Id":24026,"Amount":16584,"Pct":0.498782,"Total":16584,"Min":1,"Max":1},{"Id":24027,"Amount":16665,"Pct":0.501218,"Total":16665,"Min":1,"Max":1}]},"All":{"Total":33249,"Items":[{"Id":24026,"Amount":16584,"Pct":0.498782,"Total":16584,"Min":1,"Max":1},{"Id":24027,"Amount":16665,"Pct":0.501218,"Total":16665,"Min":1,"Max":1}]}}},{"Id":24809,"Name":"Obscure Logogram","Patches":{"7.1":{"Total":209356,"Items":[{"Id":24813,"Amount":52013,"Pct":0.248443,"Total":52013,"Min":1,"Max":1},{"Id":24810,"Amount":52343,"Pct":0.250019,"Total":52343,"Min":1,"Max":1},{"Id":24811,"Amount":52354,"Pct":0.250072,"Total":52354,"Min":1,"Max":1},{"Id":24812,"Amount":52646,"Pct":0.251466,"Total":52646,"Min":1,"Max":1}]},"7.2":{"Total":22518,"Items":[{"Id":24812,"Amount":5583,"Pct":0.247935,"Total":5583,"Min":1,"Max":1},{"Id":24813,"Amount":5584,"Pct":0.247979,"Total":5584,"Min":1,"Max":1},{"Id":24811,"Amount":5660,"Pct":0.251354,"Total":5660,"Min":1,"Max":1},{"Id":24810,"Amount":5691,"Pct":0.252731,"Total":5691,"Min":1,"Max":1}]},"7.3":{"Total":19305,"Items":[{"Id":24810,"Amount":4734,"Pct":0.245221,"Total":4734,"Min":1,"Max":1},{"Id":24812,"Amount":4824,"Pct":0.249883,"Total":4824,"Min":1,"Max":1},{"Id":24811,"Amount":4851,"Pct":0.251282,"Total":4851,"Min":1,"Max":1},{"Id":24813,"Amount":4896,"Pct":0.253613,"Total":4896,"Min":1,"Max":1}]},"All":{"Total":251179,"Items":[{"Id":24813,"Amount":62493,"Pct":0.248799,"Total":62493,"Min":1,"Max":1},{"Id":24810,"Amount":62768,"Pct":0.249894,"Total":62768,"Min":1,"Max":1},{"Id":24811,"Amount":62865,"Pct":0.25028,"Total":62865,"Min":1,"Max":1},{"Id":24812,"Amount":63053,"Pct":0.251028,"Total":63053,"Min":1,"Max":1}]}}}]},{"Name":"Fragments","TerritoryId":2,"Variants":[{"Id":30884,"Name":"Forgotten Fragment of Caution","Patches":{"7.1":{"Total":28427,"Items":[{"Id":30930,"Amount":1839,"Pct":0.064692,"Total":1839,"Min":1,"Max":1},{"Id":30904,"Amount":1859,"Pct":0.065396,"Total":1859,"Min":1,"Max":1},{"Id":30902,"Amount":2004,"Pct":0.070496,"Total":2004,"Min":1,"Max":1},{"Id":30908,"Amount":5586,"Pct":0.196503,"Total":5586,"Min":1,"Max":1},{"Id":30927,"Amount":5671,"Pct":0.199493,"Total":5671,"Min":1,"Max":1},{"Id":30925,"Amount":5676,"Pct":0.199669,"Total":5676,"Min":1,"Max":1},{"Id":30909,"Amount":5792,"Pct":0.20375,"Total":5792,"Min":1,"Max":1}]},"7.2":{"Total":5131,"Items":[{"Id":30930,"Amount":314,"Pct":0.061197,"Total":314,"Min":1,"Max":1},{"Id":30902,"Amount":315,"Pct":0.061392,"Total":315,"Min":1,"Max":1},{"Id":30904,"Amount":348,"Pct":0.067823,"Total":348,"Min":1,"Max":1},{"Id":30909,"Amount":1028,"Pct":0.200351,"Total":1028,"Min":1,"Max":1},{"Id":30908,"Amount":1034,"Pct":0.20152,"Total":1034,"Min":1,"Max":1},{"Id":30927,"Amount":1035,"Pct":0.201715,"Total":1035,"Min":1,"Max":1},{"Id":30925,"Amount":1057,"Pct":0.206003,"Total":1057,"Min":1,"Max":1}]},"7.3":{"Total":4006,"Items":[{"Id":30902,"Amount":259,"Pct":0.064653,"Total":259,"Min":1,"Max":1},{"Id":30930,"Amount":273,"Pct":0.068148,"Total":273,"Min":1,"Max":1},{"Id":30904,"Amount":299,"Pct":0.074638,"Total":299,"Min":1,"Max":1},{"Id":30925,"Amount":765,"Pct":0.190964,"Total":765,"Min":1,"Max":1},{"Id":30909,"Amount":789,"Pct":0.196955,"Total":789,"Min":1,"Max":1},{"Id":30927,"Amount":804,"Pct":0.200699,"Total":804,"Min":1,"Max":1},{"Id":30908,"Amount":817,"Pct":0.203944,"Total":817,"Min":1,"Max":1}]},"All":{"Total":37564,"Items":[{"Id":30930,"Amount":2426,"Pct":0.064583,"Total":2426,"Min":1,"Max":1},{"Id":30904,"Amount":2506,"Pct":0.066713,"Total":2506,"Min":1,"Max":1},{"Id":30902,"Amount":2578,"Pct":0.06863,"Total":2578,"Min":1,"Max":1},{"Id":30908,"Amount":7437,"Pct":0.197982,"Total":7437,"Min":1,"Max":1},{"Id":30925,"Amount":7498,"Pct":0.199606,"Total":7498,"Min":1,"Max":1},{"Id":30927,"Amount":7510,"Pct":0.199925,"Total":7510,"Min":1,"Max":1},{"Id":30909,"Amount":7609,"Pct":0.202561,"Total":7609,"Min":1,"Max":1}]}}},{"Id":30885,"Name":"Forgotten Fragment of Preparation","Patches":{"7.1":{"Total":40919,"Items":[{"Id":30934,"Amount":13661,"Pct":0.333855,"Total":13661,"Min":1,"Max":1},{"Id":30939,"Amount":27258,"Pct":0.666145,"Total":27258,"Min":1,"Max":1}]},"7.2":{"Total":5684,"Items":[{"Id":30934,"Amount":1936,"Pct":0.340605,"Total":1936,"Min":1,"Max":1},{"Id":30939,"Amount":3748,"Pct":0.659395,"Total":3748,"Min":1,"Max":1}]},"7.3":{"Total":5392,"Items":[{"Id":30934,"Amount":1794,"Pct":0.332715,"Total":1794,"Min":1,"Max":1},{"Id":30939,"Amount":3598,"Pct":0.667285,"Total":3598,"Min":1,"Max":1}]},"All":{"Total":51995,"Items":[{"Id":30934,"Amount":17391,"Pct":0.334474,"Total":17391,"Min":1,"Max":1},{"Id":30939,"Amount":34604,"Pct":0.665526,"Total":34604,"Min":1,"Max":1}]}}},{"Id":30886,"Name":"Forgotten Fragment of Skill","Patches":{"7.1":{"Total":36520,"Items":[{"Id":30942,"Amount":4083,"Pct":0.111802,"Total":4083,"Min":1,"Max":1},{"Id":30940,"Amount":7994,"Pct":0.218894,"Total":7994,"Min":1,"Max":1},{"Id":30944,"Amount":8068,"Pct":0.22092,"Total":8068,"Min":1,"Max":1},{"Id":30943,"Amount":8161,"Pct":0.223467,"Total":8161,"Min":1,"Max":1},{"Id":30941,"Amount":8214,"Pct":0.224918,"Total":8214,"Min":1,"Max":1}]},"7.2":{"Total":5401,"Items":[{"Id":30942,"Amount":617,"Pct":0.114238,"Total":617,"Min":1,"Max":1},{"Id":30940,"Amount":1153,"Pct":0.213479,"Total":1153,"Min":1,"Max":1},{"Id":30944,"Amount":1209,"Pct":0.223847,"Total":1209,"Min":1,"Max":1},{"Id":30941,"Amount":1210,"Pct":0.224033,"Total":1210,"Min":1,"Max":1},{"Id":30943,"Amount":1212,"Pct":0.224403,"Total":1212,"Min":1,"Max":1}]},"7.3":{"Total":4374,"Items":[{"Id":30942,"Amount":504,"Pct":0.115226,"Total":504,"Min":1,"Max":1},{"Id":30943,"Amount":886,"Pct":0.202561,"Total":886,"Min":1,"Max":1},{"Id":30940,"Amount":977,"Pct":0.223365,"Total":977,"Min":1,"Max":1},{"Id":30944,"Amount":1002,"Pct":0.229081,"Total":1002,"Min":1,"Max":1},{"Id":30941,"Amount":1005,"Pct":0.229767,"Total":1005,"Min":1,"Max":1}]},"All":{"Total":46295,"Items":[{"Id":30942,"Amount":5204,"Pct":0.11241,"Total":5204,"Min":1,"Max":1},{"Id":30940,"Amount":10124,"Pct":0.218685,"Total":10124,"Min":1,"Max":1},{"Id":30943,"Amount":10259,"Pct":0.221601,"Total":10259,"Min":1,"Max":1},{"Id":30944,"Amount":10279,"Pct":0.222033,"Total":10279,"Min":1,"Max":1},{"Id":30941,"Amount":10429,"Pct":0.225273,"Total":10429,"Min":1,"Max":1}]}}},{"Id":30887,"Name":"Forgotten Fragment of Ingenuity","Patches":{"7.1":{"Total":31678,"Items":[{"Id":30903,"Amount":2601,"Pct":0.082107,"Total":2601,"Min":1,"Max":1},{"Id":30905,"Amount":5304,"Pct":0.167435,"Total":5304,"Min":1,"Max":1},{"Id":30906,"Amount":5315,"Pct":0.167782,"Total":5315,"Min":1,"Max":1},{"Id":30900,"Amount":5317,"Pct":0.167845,"Total":5317,"Min":1,"Max":1},{"Id":30901,"Amount":5454,"Pct":0.17217,"Total":5454,"Min":1,"Max":1},{"Id":30907,"Amount":7687,"Pct":0.242661,"Total":7687,"Min":1,"Max":1}]},"7.2":{"Total":5530,"Items":[{"Id":30903,"Amount":411,"Pct":0.074322,"Total":411,"Min":1,"Max":1},{"Id":30905,"Amount":869,"Pct":0.157143,"Total":869,"Min":1,"Max":1},{"Id":30906,"Amount":892,"Pct":0.161302,"Total":892,"Min":1,"Max":1},{"Id":30901,"Amount":932,"Pct":0.168535,"Total":932,"Min":1,"Max":1},{"Id":30900,"Amount":967,"Pct":0.174864,"Total":967,"Min":1,"Max":1},{"Id":30907,"Amount":1459,"Pct":0.263834,"Total":1459,"Min":1,"Max":1}]},"7.3":{"Total":4824,"Items":[{"Id":30903,"Amount":371,"Pct":0.076907,"Total":371,"Min":1,"Max":1},{"Id":30905,"Amount":798,"Pct":0.165423,"Total":798,"Min":1,"Max":1},{"Id":30900,"Amount":801,"Pct":0.166045,"Total":801,"Min":1,"Max":1},{"Id":30906,"Amount":828,"Pct":0.171642,"Total":828,"Min":1,"Max":1},{"Id":30901,"Amount":841,"Pct":0.174337,"Total":841,"Min":1,"Max":1},{"Id":30907,"Amount":1185,"Pct":0.245647,"Total":1185,"Min":1,"Max":1}]},"All":{"Total":42032,"Items":[{"Id":30903,"Amount":3383,"Pct":0.080486,"Total":3383,"Min":1,"Max":1},{"Id":30905,"Amount":6971,"Pct":0.16585,"Total":6971,"Min":1,"Max":1},{"Id":30906,"Amount":7035,"Pct":0.167372,"Total":7035,"Min":1,"Max":1},{"Id":30900,"Amount":7085,"Pct":0.168562,"Total":7085,"Min":1,"Max":1},{"Id":30901,"Amount":7227,"Pct":0.17194,"Total":7227,"Min":1,"Max":1},{"Id":30907,"Amount":10331,"Pct":0.245789,"Total":10331,"Min":1,"Max":1}]}}},{"Id":30888,"Name":"Forgotten Fragment of Care","Patches":{"7.1":{"Total":106253,"Items":[{"Id":30935,"Amount":17782,"Pct":0.167355,"Total":17782,"Min":1,"Max":1},{"Id":30937,"Amount":35476,"Pct":0.333882,"Total":35476,"Min":1,"Max":1},{"Id":30936,"Amount":52995,"Pct":0.498762,"Total":52995,"Min":1,"Max":1}]},"7.2":{"Total":18239,"Items":[{"Id":30935,"Amount":3015,"Pct":0.165305,"Total":3015,"Min":1,"Max":1},{"Id":30937,"Amount":6008,"Pct":0.329404,"Total":6008,"Min":1,"Max":1},{"Id":30936,"Amount":9216,"Pct":0.505291,"Total":9216,"Min":1,"Max":1}]},"7.3":{"Total":14137,"Items":[{"Id":30935,"Amount":2345,"Pct":0.165877,"Total":2345,"Min":1,"Max":1},{"Id":30937,"Amount":4821,"Pct":0.34102,"Total":4821,"Min":1,"Max":1},{"Id":30936,"Amount":6971,"Pct":0.493103,"Total":6971,"Min":1,"Max":1}]},"All":{"Total":138629,"Items":[{"Id":30935,"Amount":23142,"Pct":0.166935,"Total":23142,"Min":1,"Max":1},{"Id":30937,"Amount":46305,"Pct":0.334021,"Total":46305,"Min":1,"Max":1},{"Id":30936,"Amount":69182,"Pct":0.499044,"Total":69182,"Min":1,"Max":1}]}}},{"Id":30889,"Name":"Forgotten Fragment of Awakening","Patches":{"7.1":{"Total":54241,"Items":[{"Id":30945,"Amount":7704,"Pct":0.142033,"Total":7704,"Min":1,"Max":1},{"Id":30948,"Amount":7714,"Pct":0.142217,"Total":7714,"Min":1,"Max":1},{"Id":30946,"Amount":7724,"Pct":0.142402,"Total":7724,"Min":1,"Max":1},{"Id":30951,"Amount":7726,"Pct":0.142438,"Total":7726,"Min":1,"Max":1},{"Id":30947,"Amount":7740,"Pct":0.142696,"Total":7740,"Min":1,"Max":1},{"Id":30949,"Amount":7792,"Pct":0.143655,"Total":7792,"Min":1,"Max":1},{"Id":30950,"Amount":7841,"Pct":0.144559,"Total":7841,"Min":1,"Max":1}]},"7.2":{"Total":7899,"Items":[{"Id":30946,"Amount":1073,"Pct":0.13584,"Total":1073,"Min":1,"Max":1},{"Id":30951,"Amount":1108,"Pct":0.140271,"Total":1108,"Min":1,"Max":1},{"Id":30945,"Amount":1111,"Pct":0.140651,"Total":1111,"Min":1,"Max":1},{"Id":30949,"Amount":1122,"Pct":0.142043,"Total":1122,"Min":1,"Max":1},{"Id":30947,"Amount":1140,"Pct":0.144322,"Total":1140,"Min":1,"Max":1},{"Id":30948,"Amount":1149,"Pct":0.145461,"Total":1149,"Min":1,"Max":1},{"Id":30950,"Amount":1196,"Pct":0.151412,"Total":1196,"Min":1,"Max":1}]},"7.3":{"Total":6845,"Items":[{"Id":30949,"Amount":956,"Pct":0.139664,"Total":956,"Min":1,"Max":1},{"Id":30950,"Amount":966,"Pct":0.141125,"Total":966,"Min":1,"Max":1},{"Id":30948,"Amount":971,"Pct":0.141855,"Total":971,"Min":1,"Max":1},{"Id":30946,"Amount":978,"Pct":0.142878,"Total":978,"Min":1,"Max":1},{"Id":30945,"Amount":983,"Pct":0.143608,"Total":983,"Min":1,"Max":1},{"Id":30951,"Amount":988,"Pct":0.144339,"Total":988,"Min":1,"Max":1},{"Id":30947,"Amount":1003,"Pct":0.14653,"Total":1003,"Min":1,"Max":1}]},"All":{"Total":68985,"Items":[{"Id":30946,"Amount":9775,"Pct":0.141697,"Total":9775,"Min":1,"Max":1},{"Id":30945,"Amount":9798,"Pct":0.142031,"Total":9798,"Min":1,"Max":1},{"Id":30951,"Amount":9822,"Pct":0.142379,"Total":9822,"Min":1,"Max":1},{"Id":30948,"Amount":9834,"Pct":0.142553,"Total":9834,"Min":1,"Max":1},{"Id":30949,"Amount":9870,"Pct":0.143075,"Total":9870,"Min":1,"Max":1},{"Id":30947,"Amount":9883,"Pct":0.143263,"Total":9883,"Min":1,"Max":1},{"Id":30950,"Amount":10003,"Pct":0.145003,"Total":10003,"Min":1,"Max":1}]}}},{"Id":30890,"Name":"Forgotten Fragment of Support","Patches":{"7.1":{"Total":28139,"Items":[{"Id":30912,"Amount":5703,"Pct":0.202672,"Total":5703,"Min":1,"Max":1},{"Id":30911,"Amount":11117,"Pct":0.395074,"Total":11117,"Min":1,"Max":1},{"Id":30910,"Amount":11319,"Pct":0.402253,"Total":11319,"Min":1,"Max":1}]},"7.2":{"Total":2866,"Items":[{"Id":30912,"Amount":559,"Pct":0.195045,"Total":559,"Min":1,"Max":1},{"Id":30911,"Amount":1144,"Pct":0.399163,"Total":1144,"Min":1,"Max":1},{"Id":30910,"Amount":1163,"Pct":0.405792,"Total":1163,"Min":1,"Max":1}]},"7.3":{"Total":6174,"Items":[{"Id":30912,"Amount":1236,"Pct":0.200194,"Total":1236,"Min":1,"Max":1},{"Id":30911,"Amount":2467,"Pct":0.399579,"Total":2467,"Min":1,"Max":1},{"Id":30910,"Amount":2471,"Pct":0.400227,"Total":2471,"Min":1,"Max":1}]},"All":{"Total":37179,"Items":[{"Id":30912,"Amount":7498,"Pct":0.201673,"Total":7498,"Min":1,"Max":1},{"Id":30911,"Amount":14728,"Pct":0.396138,"Total":14728,"Min":1,"Max":1},{"Id":30910,"Amount":14953,"Pct":0.402189,"Total":14953,"Min":1,"Max":1}]}}},{"Id":30891,"Name":"Forgotten Fragment of Violence","Patches":{"7.1":{"Total":46321,"Items":[{"Id":30917,"Amount":4522,"Pct":0.097623,"Total":4522,"Min":1,"Max":1},{"Id":30913,"Amount":14130,"Pct":0.305045,"Total":14130,"Min":1,"Max":1},{"Id":30918,"Amount":27669,"Pct":0.597332,"Total":27669,"Min":1,"Max":1}]},"7.2":{"Total":6881,"Items":[{"Id":30917,"Amount":699,"Pct":0.101584,"Total":699,"Min":1,"Max":1},{"Id":30913,"Amount":2006,"Pct":0.291527,"Total":2006,"Min":1,"Max":1},{"Id":30918,"Amount":4176,"Pct":0.606889,"Total":4176,"Min":1,"Max":1}]},"7.3":{"Total":5708,"Items":[{"Id":30917,"Amount":552,"Pct":0.096706,"Total":552,"Min":1,"Max":1},{"Id":30913,"Amount":1765,"Pct":0.309215,"Total":1765,"Min":1,"Max":1},{"Id":30918,"Amount":3391,"Pct":0.594078,"Total":3391,"Min":1,"Max":1}]},"All":{"Total":58910,"Items":[{"Id":30917,"Amount":5773,"Pct":0.097997,"Total":5773,"Min":1,"Max":1},{"Id":30913,"Amount":17901,"Pct":0.30387,"Total":17901,"Min":1,"Max":1},{"Id":30918,"Amount":35236,"Pct":0.598133,"Total":35236,"Min":1,"Max":1}]}}},{"Id":30892,"Name":"Forgotten Fragment of Resolve","Patches":{"7.1":{"Total":54438,"Items":[{"Id":30921,"Amount":5435,"Pct":0.099838,"Total":5435,"Min":1,"Max":1},{"Id":30922,"Amount":5472,"Pct":0.100518,"Total":5472,"Min":1,"Max":1},{"Id":30923,"Amount":10768,"Pct":0.197803,"Total":10768,"Min":1,"Max":1},{"Id":30924,"Amount":10883,"Pct":0.199916,"Total":10883,"Min":1,"Max":1},{"Id":30919,"Amount":10911,"Pct":0.20043,"Total":10911,"Min":1,"Max":1},{"Id":30920,"Amount":10969,"Pct":0.201495,"Total":10969,"Min":1,"Max":1}]},"7.2":{"Total":6812,"Items":[{"Id":30922,"Amount":689,"Pct":0.101145,"Total":689,"Min":1,"Max":1},{"Id":30921,"Amount":700,"Pct":0.10276,"Total":700,"Min":1,"Max":1},{"Id":30919,"Amount":1302,"Pct":0.191133,"Total":1302,"Min":1,"Max":1},{"Id":30920,"Amount":1353,"Pct":0.19862,"Total":1353,"Min":1,"Max":1},{"Id":30923,"Amount":1361,"Pct":0.199794,"Total":1361,"Min":1,"Max":1},{"Id":30924,"Amount":1407,"Pct":0.206547,"Total":1407,"Min":1,"Max":1}]},"7.3":{"Total":6404,"Items":[{"Id":30922,"Amount":636,"Pct":0.099313,"Total":636,"Min":1,"Max":1},{"Id":30921,"Amount":641,"Pct":0.100094,"Total":641,"Min":1,"Max":1},{"Id":30920,"Amount":1223,"Pct":0.190974,"Total":1223,"Min":1,"Max":1},{"Id":30924,"Amount":1257,"Pct":0.196284,"Total":1257,"Min":1,"Max":1},{"Id":30923,"Amount":1318,"Pct":0.205809,"Total":1318,"Min":1,"Max":1},{"Id":30919,"Amount":1329,"Pct":0.207527,"Total":1329,"Min":1,"Max":1}]},"All":{"Total":67654,"Items":[{"Id":30921,"Amount":6776,"Pct":0.100157,"Total":6776,"Min":1,"Max":1},{"Id":30922,"Amount":6797,"Pct":0.100467,"Total":6797,"Min":1,"Max":1},{"Id":30923,"Amount":13447,"Pct":0.198761,"Total":13447,"Min":1,"Max":1},{"Id":30919,"Amount":13542,"Pct":0.200166,"Total":13542,"Min":1,"Max":1},{"Id":30920,"Amount":13545,"Pct":0.20021,"Total":13545,"Min":1,"Max":1},{"Id":30924,"Amount":13547,"Pct":0.200239,"Total":13547,"Min":1,"Max":1}]}}},{"Id":30893,"Name":"Forgotten Fragment of Compassion","Patches":{"7.1":{"Total":43235,"Items":[{"Id":30938,"Amount":3020,"Pct":0.069851,"Total":3020,"Min":1,"Max":1},{"Id":30929,"Amount":9172,"Pct":0.212143,"Total":9172,"Min":1,"Max":1},{"Id":30928,"Amount":15511,"Pct":0.35876,"Total":15511,"Min":1,"Max":1},{"Id":30926,"Amount":15532,"Pct":0.359246,"Total":15532,"Min":1,"Max":1}]},"7.2":{"Total":5698,"Items":[{"Id":30938,"Amount":430,"Pct":0.075465,"Total":430,"Min":1,"Max":1},{"Id":30929,"Amount":1231,"Pct":0.216041,"Total":1231,"Min":1,"Max":1},{"Id":30928,"Amount":1989,"Pct":0.34907,"Total":1989,"Min":1,"Max":1},{"Id":30926,"Amount":2048,"Pct":0.359424,"Total":2048,"Min":1,"Max":1}]},"7.3":{"Total":3432,"Items":[{"Id":30938,"Amount":248,"Pct":0.072261,"Total":248,"Min":1,"Max":1},{"Id":30929,"Amount":672,"Pct":0.195804,"Total":672,"Min":1,"Max":1},{"Id":30926,"Amount":1246,"Pct":0.363054,"Total":1246,"Min":1,"Max":1},{"Id":30928,"Amount":1266,"Pct":0.368881,"Total":1266,"Min":1,"Max":1}]},"All":{"Total":52365,"Items":[{"Id":30938,"Amount":3698,"Pct":0.07062,"Total":3698,"Min":1,"Max":1},{"Id":30929,"Amount":11075,"Pct":0.211496,"Total":11075,"Min":1,"Max":1},{"Id":30928,"Amount":18766,"Pct":0.358369,"Total":18766,"Min":1,"Max":1},{"Id":30926,"Amount":18826,"Pct":0.359515,"Total":18826,"Min":1,"Max":1}]}}},{"Id":30894,"Name":"Forgotten Fragment of Superstition","Patches":{"7.1":{"Total":26193,"Items":[{"Id":30952,"Amount":8700,"Pct":0.33215,"Total":8700,"Min":1,"Max":1},{"Id":30953,"Amount":8720,"Pct":0.332913,"Total":8720,"Min":1,"Max":1},{"Id":30954,"Amount":8773,"Pct":0.334937,"Total":8773,"Min":1,"Max":1}]},"7.2":{"Total":3515,"Items":[{"Id":30953,"Amount":1122,"Pct":0.319203,"Total":1122,"Min":1,"Max":1},{"Id":30954,"Amount":1178,"Pct":0.335135,"Total":1178,"Min":1,"Max":1},{"Id":30952,"Amount":1215,"Pct":0.345661,"Total":1215,"Min":1,"Max":1}]},"7.3":{"Total":3179,"Items":[{"Id":30952,"Amount":1031,"Pct":0.324316,"Total":1031,"Min":1,"Max":1},{"Id":30953,"Amount":1066,"Pct":0.335326,"Total":1066,"Min":1,"Max":1},{"Id":30954,"Amount":1082,"Pct":0.340359,"Total":1082,"Min":1,"Max":1}]},"All":{"Total":32887,"Items":[{"Id":30953,"Amount":10908,"Pct":0.331681,"Total":10908,"Min":1,"Max":1},{"Id":30952,"Amount":10946,"Pct":0.332837,"Total":10946,"Min":1,"Max":1},{"Id":30954,"Amount":11033,"Pct":0.335482,"Total":11033,"Min":1,"Max":1}]}}},{"Id":30895,"Name":"Forgotten Fragment of Mastery","Patches":{"7.1":{"Total":27137,"Items":[{"Id":30957,"Amount":2990,"Pct":0.110182,"Total":2990,"Min":1,"Max":1},{"Id":30955,"Amount":6006,"Pct":0.221321,"Total":6006,"Min":1,"Max":1},{"Id":30956,"Amount":6022,"Pct":0.221911,"Total":6022,"Min":1,"Max":1},{"Id":30958,"Amount":6057,"Pct":0.223201,"Total":6057,"Min":1,"Max":1},{"Id":30959,"Amount":6062,"Pct":0.223385,"Total":6062,"Min":1,"Max":1}]},"7.2":{"Total":3543,"Items":[{"Id":30957,"Amount":373,"Pct":0.105278,"Total":373,"Min":1,"Max":1},{"Id":30959,"Amount":744,"Pct":0.209992,"Total":744,"Min":1,"Max":1},{"Id":30955,"Amount":757,"Pct":0.213661,"Total":757,"Min":1,"Max":1},{"Id":30956,"Amount":821,"Pct":0.231725,"Total":821,"Min":1,"Max":1},{"Id":30958,"Amount":848,"Pct":0.239345,"Total":848,"Min":1,"Max":1}]},"7.3":{"Total":3333,"Items":[{"Id":30957,"Amount":373,"Pct":0.111911,"Total":373,"Min":1,"Max":1},{"Id":30959,"Amount":713,"Pct":0.213921,"Total":713,"Min":1,"Max":1},{"Id":30955,"Amount":720,"Pct":0.216022,"Total":720,"Min":1,"Max":1},{"Id":30956,"Amount":759,"Pct":0.227723,"Total":759,"Min":1,"Max":1},{"Id":30958,"Amount":768,"Pct":0.230423,"Total":768,"Min":1,"Max":1}]},"All":{"Total":34013,"Items":[{"Id":30957,"Amount":3736,"Pct":0.10984,"Total":3736,"Min":1,"Max":1},{"Id":30955,"Amount":7483,"Pct":0.220004,"Total":7483,"Min":1,"Max":1},{"Id":30959,"Amount":7519,"Pct":0.221063,"Total":7519,"Min":1,"Max":1},{"Id":30956,"Amount":7602,"Pct":0.223503,"Total":7602,"Min":1,"Max":1},{"Id":30958,"Amount":7673,"Pct":0.22559,"Total":7673,"Min":1,"Max":1}]}}},{"Id":30896,"Name":"Forgotten Fragment of Sagacity","Patches":{"7.1":{"Total":34129,"Items":[{"Id":30915,"Amount":3019,"Pct":0.088458,"Total":3019,"Min":1,"Max":1},{"Id":30914,"Amount":15551,"Pct":0.455654,"Total":15551,"Min":1,"Max":1},{"Id":30916,"Amount":15559,"Pct":0.455888,"Total":15559,"Min":1,"Max":1}]},"7.2":{"Total":3846,"Items":[{"Id":30915,"Amount":349,"Pct":0.090744,"Total":349,"Min":1,"Max":1},{"Id":30914,"Amount":1738,"Pct":0.451898,"Total":1738,"Min":1,"Max":1},{"Id":30916,"Amount":1759,"Pct":0.457358,"Total":1759,"Min":1,"Max":1}]},"7.3":{"Total":4154,"Items":[{"Id":30915,"Amount":380,"Pct":0.091478,"Total":380,"Min":1,"Max":1},{"Id":30914,"Amount":1868,"Pct":0.449687,"Total":1868,"Min":1,"Max":1},{"Id":30916,"Amount":1906,"Pct":0.458835,"Total":1906,"Min":1,"Max":1}]},"All":{"Total":42129,"Items":[{"Id":30915,"Amount":3748,"Pct":0.088965,"Total":3748,"Min":1,"Max":1},{"Id":30914,"Amount":19157,"Pct":0.454722,"Total":19157,"Min":1,"Max":1},{"Id":30916,"Amount":19224,"Pct":0.456313,"Total":19224,"Min":1,"Max":1}]}}},{"Id":30897,"Name":"Forgotten Fragment of Becoming","Patches":{"7.1":{"Total":22416,"Items":[{"Id":30960,"Amount":3137,"Pct":0.139945,"Total":3137,"Min":1,"Max":1},{"Id":30965,"Amount":3194,"Pct":0.142488,"Total":3194,"Min":1,"Max":1},{"Id":30961,"Amount":3197,"Pct":0.142621,"Total":3197,"Min":1,"Max":1},{"Id":30963,"Amount":3205,"Pct":0.142978,"Total":3205,"Min":1,"Max":1},{"Id":30964,"Amount":3215,"Pct":0.143424,"Total":3215,"Min":1,"Max":1},{"Id":30966,"Amount":3219,"Pct":0.143603,"Total":3219,"Min":1,"Max":1},{"Id":30962,"Amount":3249,"Pct":0.144941,"Total":3249,"Min":1,"Max":1}]},"7.2":{"Total":2172,"Items":[{"Id":30965,"Amount":293,"Pct":0.134899,"Total":293,"Min":1,"Max":1},{"Id":30961,"Amount":308,"Pct":0.141805,"Total":308,"Min":1,"Max":1},{"Id":30966,"Amount":312,"Pct":0.143646,"Total":312,"Min":1,"Max":1},{"Id":30960,"Amount":313,"Pct":0.144107,"Total":313,"Min":1,"Max":1},{"Id":30962,"Amount":313,"Pct":0.144107,"Total":313,"Min":1,"Max":1},{"Id":30963,"Amount":313,"Pct":0.144107,"Total":313,"Min":1,"Max":1},{"Id":30964,"Amount":320,"Pct":0.14733,"Total":320,"Min":1,"Max":1}]},"7.3":{"Total":2155,"Items":[{"Id":30963,"Amount":281,"Pct":0.130394,"Total":281,"Min":1,"Max":1},{"Id":30961,"Amount":303,"Pct":0.140603,"Total":303,"Min":1,"Max":1},{"Id":30960,"Amount":305,"Pct":0.141531,"Total":305,"Min":1,"Max":1},{"Id":30962,"Amount":305,"Pct":0.141531,"Total":305,"Min":1,"Max":1},{"Id":30966,"Amount":318,"Pct":0.147564,"Total":318,"Min":1,"Max":1},{"Id":30964,"Amount":320,"Pct":0.148492,"Total":320,"Min":1,"Max":1},{"Id":30965,"Amount":323,"Pct":0.149884,"Total":323,"Min":1,"Max":1}]},"All":{"Total":26743,"Items":[{"Id":30960,"Amount":3755,"Pct":0.140411,"Total":3755,"Min":1,"Max":1},{"Id":30963,"Amount":3799,"Pct":0.142056,"Total":3799,"Min":1,"Max":1},{"Id":30961,"Amount":3808,"Pct":0.142392,"Total":3808,"Min":1,"Max":1},{"Id":30965,"Amount":3810,"Pct":0.142467,"Total":3810,"Min":1,"Max":1},{"Id":30966,"Amount":3849,"Pct":0.143926,"Total":3849,"Min":1,"Max":1},{"Id":30964,"Amount":3855,"Pct":0.14415,"Total":3855,"Min":1,"Max":1},{"Id":30962,"Amount":3867,"Pct":0.144599,"Total":3867,"Min":1,"Max":1}]}}},{"Id":30898,"Name":"Forgotten Fragment of Transcendence","Patches":{"7.1":{"Total":16439,"Items":[{"Id":30968,"Amount":5432,"Pct":0.330434,"Total":5432,"Min":1,"Max":1},{"Id":30967,"Amount":5474,"Pct":0.332989,"Total":5474,"Min":1,"Max":1},{"Id":30969,"Amount":5533,"Pct":0.336578,"Total":5533,"Min":1,"Max":1}]},"7.2":{"Total":1701,"Items":[{"Id":30968,"Amount":550,"Pct":0.323339,"Total":550,"Min":1,"Max":1},{"Id":30967,"Amount":555,"Pct":0.326279,"Total":555,"Min":1,"Max":1},{"Id":30969,"Amount":596,"Pct":0.350382,"Total":596,"Min":1,"Max":1}]},"7.3":{"Total":1524,"Items":[{"Id":30967,"Amount":472,"Pct":0.309711,"Total":472,"Min":1,"Max":1},{"Id":30969,"Amount":525,"Pct":0.344488,"Total":525,"Min":1,"Max":1},{"Id":30968,"Amount":527,"Pct":0.345801,"Total":527,"Min":1,"Max":1}]},"All":{"Total":19664,"Items":[{"Id":30967,"Amount":6501,"Pct":0.330604,"Total":6501,"Min":1,"Max":1},{"Id":30968,"Amount":6509,"Pct":0.331011,"Total":6509,"Min":1,"Max":1},{"Id":30969,"Amount":6654,"Pct":0.338385,"Total":6654,"Min":1,"Max":1}]}}},{"Id":30899,"Name":"Forgotten Fragment of Caprice","Patches":{"7.1":{"Total":20356,"Items":[{"Id":30931,"Amount":2052,"Pct":0.100806,"Total":2052,"Min":1,"Max":1},{"Id":30932,"Amount":4062,"Pct":0.199548,"Total":4062,"Min":1,"Max":1},{"Id":30933,"Amount":14242,"Pct":0.699646,"Total":14242,"Min":1,"Max":1}]},"7.2":{"Total":2671,"Items":[{"Id":30931,"Amount":283,"Pct":0.105953,"Total":283,"Min":1,"Max":1},{"Id":30932,"Amount":496,"Pct":0.185698,"Total":496,"Min":1,"Max":1},{"Id":30933,"Amount":1892,"Pct":0.708349,"Total":1892,"Min":1,"Max":1}]},"7.3":{"Total":2074,"Items":[{"Id":30931,"Amount":235,"Pct":0.113308,"Total":235,"Min":1,"Max":1},{"Id":30932,"Amount":416,"Pct":0.200579,"Total":416,"Min":1,"Max":1},{"Id":30933,"Amount":1423,"Pct":0.686114,"Total":1423,"Min":1,"Max":1}]},"All":{"Total":25101,"Items":[{"Id":30931,"Amount":2570,"Pct":0.102386,"Total":2570,"Min":1,"Max":1},{"Id":30932,"Amount":4974,"Pct":0.198159,"Total":4974,"Min":1,"Max":1},{"Id":30933,"Amount":17557,"Pct":0.699454,"Total":17557,"Min":1,"Max":1}]}}},{"Id":32162,"Name":"Forgotten Fragment of Observation","Patches":{"7.1":{"Total":2498,"Items":[{"Id":32166,"Amount":2498,"Pct":1.0,"Total":2498,"Min":1,"Max":1}]},"7.2":{"Total":452,"Items":[{"Id":32166,"Amount":452,"Pct":1.0,"Total":452,"Min":1,"Max":1}]},"7.3":{"Total":367,"Items":[{"Id":32166,"Amount":367,"Pct":1.0,"Total":367,"Min":1,"Max":1}]},"All":{"Total":3317,"Items":[{"Id":32166,"Amount":3317,"Pct":1.0,"Total":3317,"Min":1,"Max":1}]}}},{"Id":32163,"Name":"Forgotten Fragment of Deception","Patches":{"7.1":{"Total":1125,"Items":[{"Id":32168,"Amount":1125,"Pct":1.0,"Total":1125,"Min":1,"Max":1}]},"7.2":{"Total":226,"Items":[{"Id":32168,"Amount":226,"Pct":1.0,"Total":226,"Min":1,"Max":1}]},"7.3":{"Total":157,"Items":[{"Id":32168,"Amount":157,"Pct":1.0,"Total":157,"Min":1,"Max":1}]},"All":{"Total":1508,"Items":[{"Id":32168,"Amount":1508,"Pct":1.0,"Total":1508,"Min":1,"Max":1}]}}},{"Id":32164,"Name":"Forgotten Fragment of Loss","Patches":{"7.1":{"Total":5613,"Items":[{"Id":32167,"Amount":5613,"Pct":1.0,"Total":5613,"Min":1,"Max":1}]},"7.2":{"Total":1188,"Items":[{"Id":32167,"Amount":1188,"Pct":1.0,"Total":1188,"Min":1,"Max":1}]},"7.3":{"Total":769,"Items":[{"Id":32167,"Amount":769,"Pct":1.0,"Total":769,"Min":1,"Max":1}]},"All":{"Total":7570,"Items":[{"Id":32167,"Amount":7570,"Pct":1.0,"Total":7570,"Min":1,"Max":1}]}}},{"Id":32165,"Name":"Forgotten Fragment of Clarity","Patches":{"7.1":{"Total":15979,"Items":[{"Id":32169,"Amount":5312,"Pct":0.332436,"Total":5312,"Min":1,"Max":1},{"Id":32174,"Amount":10667,"Pct":0.667564,"Total":10667,"Min":1,"Max":1}]},"7.2":{"Total":2719,"Items":[{"Id":32169,"Amount":917,"Pct":0.337256,"Total":917,"Min":1,"Max":1},{"Id":32174,"Amount":1802,"Pct":0.662744,"Total":1802,"Min":1,"Max":1}]},"7.3":{"Total":2355,"Items":[{"Id":32169,"Amount":803,"Pct":0.340977,"Total":803,"Min":1,"Max":1},{"Id":32174,"Amount":1552,"Pct":0.659023,"Total":1552,"Min":1,"Max":1}]},"All":{"Total":21053,"Items":[{"Id":32169,"Amount":7032,"Pct":0.334014,"Total":7032,"Min":1,"Max":1},{"Id":32174,"Amount":14021,"Pct":0.665986,"Total":14021,"Min":1,"Max":1}]}}},{"Id":32831,"Name":"Forgotten Fragment of Contention","Patches":{"7.1":{"Total":13187,"Items":[{"Id":32170,"Amount":4371,"Pct":0.331463,"Total":4371,"Min":1,"Max":1},{"Id":32175,"Amount":8816,"Pct":0.668537,"Total":8816,"Min":1,"Max":1}]},"7.2":{"Total":1588,"Items":[{"Id":32170,"Amount":525,"Pct":0.330605,"Total":525,"Min":1,"Max":1},{"Id":32175,"Amount":1063,"Pct":0.669395,"Total":1063,"Min":1,"Max":1}]},"7.3":{"Total":2005,"Items":[{"Id":32170,"Amount":648,"Pct":0.323192,"Total":648,"Min":1,"Max":1},{"Id":32175,"Amount":1357,"Pct":0.676808,"Total":1357,"Min":1,"Max":1}]},"All":{"Total":16780,"Items":[{"Id":32170,"Amount":5544,"Pct":0.330393,"Total":5544,"Min":1,"Max":1},{"Id":32175,"Amount":11236,"Pct":0.669607,"Total":11236,"Min":1,"Max":1}]}}},{"Id":32832,"Name":"Forgotten Fragment of Finesse","Patches":{"7.1":{"Total":9610,"Items":[{"Id":32171,"Amount":3229,"Pct":0.336004,"Total":3229,"Min":1,"Max":1},{"Id":32178,"Amount":6381,"Pct":0.663996,"Total":6381,"Min":1,"Max":1}]},"7.2":{"Total":1221,"Items":[{"Id":32171,"Amount":409,"Pct":0.334971,"Total":409,"Min":1,"Max":1},{"Id":32178,"Amount":812,"Pct":0.665029,"Total":812,"Min":1,"Max":1}]},"7.3":{"Total":1382,"Items":[{"Id":32171,"Amount":468,"Pct":0.33864,"Total":468,"Min":1,"Max":1},{"Id":32178,"Amount":914,"Pct":0.66136,"Total":914,"Min":1,"Max":1}]},"All":{"Total":12213,"Items":[{"Id":32171,"Amount":4106,"Pct":0.336199,"Total":4106,"Min":1,"Max":1},{"Id":32178,"Amount":8107,"Pct":0.663801,"Total":8107,"Min":1,"Max":1}]}}},{"Id":32833,"Name":"Forgotten Fragment of Fortitude","Patches":{"7.1":{"Total":7835,"Items":[{"Id":32172,"Amount":2598,"Pct":0.331589,"Total":2598,"Min":1,"Max":1},{"Id":32177,"Amount":5237,"Pct":0.668411,"Total":5237,"Min":1,"Max":1}]},"7.2":{"Total":1807,"Items":[{"Id":32172,"Amount":631,"Pct":0.349198,"Total":631,"Min":1,"Max":1},{"Id":32177,"Amount":1176,"Pct":0.650802,"Total":1176,"Min":1,"Max":1}]},"7.3":{"Total":1428,"Items":[{"Id":32172,"Amount":455,"Pct":0.318627,"Total":455,"Min":1,"Max":1},{"Id":32177,"Amount":973,"Pct":0.681373,"Total":973,"Min":1,"Max":1}]},"All":{"Total":11070,"Items":[{"Id":32172,"Amount":3684,"Pct":0.332791,"Total":3684,"Min":1,"Max":1},{"Id":32177,"Amount":7386,"Pct":0.667209,"Total":7386,"Min":1,"Max":1}]}}},{"Id":32834,"Name":"Forgotten Fragment of Divinity","Patches":{"7.1":{"Total":9923,"Items":[{"Id":32173,"Amount":3327,"Pct":0.335282,"Total":3327,"Min":1,"Max":1},{"Id":32176,"Amount":6596,"Pct":0.664718,"Total":6596,"Min":1,"Max":1}]},"7.2":{"Total":1684,"Items":[{"Id":32173,"Amount":600,"Pct":0.356295,"Total":600,"Min":1,"Max":1},{"Id":32176,"Amount":1084,"Pct":0.643705,"Total":1084,"Min":1,"Max":1}]},"7.3":{"Total":2214,"Items":[{"Id":32173,"Amount":787,"Pct":0.355465,"Total":787,"Min":1,"Max":1},{"Id":32176,"Amount":1427,"Pct":0.644535,"Total":1427,"Min":1,"Max":1}]},"All":{"Total":13821,"Items":[{"Id":32173,"Amount":4714,"Pct":0.341075,"Total":4714,"Min":1,"Max":1},{"Id":32176,"Amount":9107,"Pct":0.658925,"Total":9107,"Min":1,"Max":1}]}}},{"Id":33768,"Name":"Forgotten Fragment of History","Patches":{"7.1":{"Total":19022,"Items":[{"Id":33780,"Amount":19022,"Pct":1.0,"Total":19022,"Min":1,"Max":1}]},"7.2":{"Total":2130,"Items":[{"Id":33780,"Amount":2130,"Pct":1.0,"Total":2130,"Min":1,"Max":1}]},"7.3":{"Total":2106,"Items":[{"Id":33780,"Amount":2106,"Pct":1.0,"Total":2106,"Min":1,"Max":1}]},"All":{"Total":23258,"Items":[{"Id":33780,"Amount":23258,"Pct":1.0,"Total":23258,"Min":1,"Max":1}]}}},{"Id":33769,"Name":"Forgotten Fragment of Rage","Patches":{"7.1":{"Total":16395,"Items":[{"Id":33782,"Amount":8097,"Pct":0.49387,"Total":8097,"Min":1,"Max":1},{"Id":33781,"Amount":8298,"Pct":0.50613,"Total":8298,"Min":1,"Max":1}]},"7.2":{"Total":1609,"Items":[{"Id":33781,"Amount":789,"Pct":0.490367,"Total":789,"Min":1,"Max":1},{"Id":33782,"Amount":820,"Pct":0.509633,"Total":820,"Min":1,"Max":1}]},"7.3":{"Total":2184,"Items":[{"Id":33782,"Amount":1055,"Pct":0.483059,"Total":1055,"Min":1,"Max":1},{"Id":33781,"Amount":1129,"Pct":0.516941,"Total":1129,"Min":1,"Max":1}]},"All":{"Total":20188,"Items":[{"Id":33782,"Amount":9972,"Pct":0.493957,"Total":9972,"Min":1,"Max":1},{"Id":33781,"Amount":10216,"Pct":0.506043,"Total":10216,"Min":1,"Max":1}]}}},{"Id":33770,"Name":"Forgotten Fragment of Ferocity","Patches":{"7.1":{"Total":12527,"Items":[{"Id":33781,"Amount":6260,"Pct":0.499721,"Total":6260,"Min":1,"Max":1},{"Id":33783,"Amount":6267,"Pct":0.500279,"Total":6267,"Min":1,"Max":1}]},"7.2":{"Total":1087,"Items":[{"Id":33781,"Amount":529,"Pct":0.486661,"Total":529,"Min":1,"Max":1},{"Id":33783,"Amount":558,"Pct":0.513339,"Total":558,"Min":1,"Max":1}]},"7.3":{"Total":1736,"Items":[{"Id":33781,"Amount":861,"Pct":0.495968,"Total":861,"Min":1,"Max":1},{"Id":33783,"Amount":875,"Pct":0.504032,"Total":875,"Min":1,"Max":1}]},"All":{"Total":15350,"Items":[{"Id":33781,"Amount":7650,"Pct":0.498371,"Total":7650,"Min":1,"Max":1},{"Id":33783,"Amount":7700,"Pct":0.501629,"Total":7700,"Min":1,"Max":1}]}}},{"Id":33771,"Name":"Forgotten Fragment of Moonlight","Patches":{"7.1":{"Total":9823,"Items":[{"Id":33784,"Amount":9823,"Pct":1.0,"Total":9823,"Min":1,"Max":1}]},"7.2":{"Total":1742,"Items":[{"Id":33784,"Amount":1742,"Pct":1.0,"Total":1742,"Min":1,"Max":1}]},"7.3":{"Total":1446,"Items":[{"Id":33784,"Amount":1446,"Pct":1.0,"Total":1446,"Min":1,"Max":1}]},"All":{"Total":13011,"Items":[{"Id":33784,"Amount":13011,"Pct":1.0,"Total":13011,"Min":1,"Max":1}]}}},{"Id":33772,"Name":"Forgotten Fragment of Hope","Patches":{"7.1":{"Total":3511,"Items":[{"Id":33785,"Amount":3511,"Pct":1.0,"Total":3511,"Min":1,"Max":1}]},"7.2":{"Total":540,"Items":[{"Id":33785,"Amount":540,"Pct":1.0,"Total":540,"Min":1,"Max":1}]},"7.3":{"Total":435,"Items":[{"Id":33785,"Amount":435,"Pct":1.0,"Total":435,"Min":1,"Max":1}]},"All":{"Total":4486,"Items":[{"Id":33785,"Amount":4486,"Pct":1.0,"Total":4486,"Min":1,"Max":1}]}}},{"Id":33773,"Name":"Forgotten Fragment of Artistry","Patches":{"7.1":{"Total":22270,"Items":[{"Id":33786,"Amount":11057,"Pct":0.496498,"Total":11057,"Min":1,"Max":1},{"Id":33787,"Amount":11213,"Pct":0.503502,"Total":11213,"Min":1,"Max":1}]},"7.2":{"Total":3355,"Items":[{"Id":33787,"Amount":1657,"Pct":0.49389,"Total":1657,"Min":1,"Max":1},{"Id":33786,"Amount":1698,"Pct":0.50611,"Total":1698,"Min":1,"Max":1}]},"7.3":{"Total":3383,"Items":[{"Id":33786,"Amount":1684,"Pct":0.497783,"Total":1684,"Min":1,"Max":1},{"Id":33787,"Amount":1699,"Pct":0.502217,"Total":1699,"Min":1,"Max":1}]},"All":{"Total":29008,"Items":[{"Id":33786,"Amount":14439,"Pct":0.497759,"Total":14439,"Min":1,"Max":1},{"Id":33787,"Amount":14569,"Pct":0.502241,"Total":14569,"Min":1,"Max":1}]}}},{"Id":33774,"Name":"Forgotten Fragment of Desperation","Patches":{"7.1":{"Total":19139,"Items":[{"Id":33788,"Amount":9529,"Pct":0.497884,"Total":9529,"Min":1,"Max":1},{"Id":33789,"Amount":9610,"Pct":0.502116,"Total":9610,"Min":1,"Max":1}]},"7.2":{"Total":1732,"Items":[{"Id":33789,"Amount":858,"Pct":0.495381,"Total":858,"Min":1,"Max":1},{"Id":33788,"Amount":874,"Pct":0.504619,"Total":874,"Min":1,"Max":1}]},"7.3":{"Total":1503,"Items":[{"Id":33789,"Amount":738,"Pct":0.491018,"Total":738,"Min":1,"Max":1},{"Id":33788,"Amount":765,"Pct":0.508982,"Total":765,"Min":1,"Max":1}]},"All":{"Total":22374,"Items":[{"Id":33788,"Amount":11168,"Pct":0.499151,"Total":11168,"Min":1,"Max":1},{"Id":33789,"Amount":11206,"Pct":0.500849,"Total":11206,"Min":1,"Max":1}]}}},{"Id":33775,"Name":"Forgotten Fragment of Tenacity","Patches":{"7.1":{"Total":50071,"Items":[{"Id":33790,"Amount":50071,"Pct":1.0,"Total":50071,"Min":1,"Max":1}]},"7.2":{"Total":4717,"Items":[{"Id":33790,"Amount":4717,"Pct":1.0,"Total":4717,"Min":1,"Max":1}]},"7.3":{"Total":3609,"Items":[{"Id":33790,"Amount":3609,"Pct":1.0,"Total":3609,"Min":1,"Max":1}]},"All":{"Total":58397,"Items":[{"Id":33790,"Amount":58397,"Pct":1.0,"Total":58397,"Min":1,"Max":1}]}}},{"Id":33776,"Name":"Forgotten Fragment of Inspiration","Patches":{"7.1":{"Total":7518,"Items":[{"Id":33791,"Amount":7518,"Pct":1.0,"Total":7518,"Min":1,"Max":1}]},"7.2":{"Total":958,"Items":[{"Id":33791,"Amount":958,"Pct":1.0,"Total":958,"Min":1,"Max":1}]},"7.3":{"Total":1256,"Items":[{"Id":33791,"Amount":1256,"Pct":1.0,"Total":1256,"Min":1,"Max":1}]},"All":{"Total":9732,"Items":[{"Id":33791,"Amount":9732,"Pct":1.0,"Total":9732,"Min":1,"Max":1}]}}},{"Id":33777,"Name":"Forgotten Fragment of Heroism","Patches":{"7.1":{"Total":5949,"Items":[{"Id":33792,"Amount":2957,"Pct":0.497058,"Total":2957,"Min":1,"Max":1},{"Id":33795,"Amount":2992,"Pct":0.502942,"Total":2992,"Min":1,"Max":1}]},"7.2":{"Total":734,"Items":[{"Id":33792,"Amount":345,"Pct":0.470027,"Total":345,"Min":1,"Max":1},{"Id":33795,"Amount":389,"Pct":0.529973,"Total":389,"Min":1,"Max":1}]},"7.3":{"Total":424,"Items":[{"Id":33792,"Amount":210,"Pct":0.495283,"Total":210,"Min":1,"Max":1},{"Id":33795,"Amount":214,"Pct":0.504717,"Total":214,"Min":1,"Max":1}]},"All":{"Total":7107,"Items":[{"Id":33792,"Amount":3512,"Pct":0.494161,"Total":3512,"Min":1,"Max":1},{"Id":33795,"Amount":3595,"Pct":0.505839,"Total":3595,"Min":1,"Max":1}]}}},{"Id":33778,"Name":"Forgotten Fragment of Revelation","Patches":{"7.1":{"Total":3635,"Items":[{"Id":33793,"Amount":1816,"Pct":0.499587,"Total":1816,"Min":1,"Max":1},{"Id":33795,"Amount":1819,"Pct":0.500413,"Total":1819,"Min":1,"Max":1}]},"7.2":{"Total":514,"Items":[{"Id":33795,"Amount":250,"Pct":0.486381,"Total":250,"Min":1,"Max":1},{"Id":33793,"Amount":264,"Pct":0.513619,"Total":264,"Min":1,"Max":1}]},"7.3":{"Total":346,"Items":[{"Id":33795,"Amount":173,"Pct":0.5,"Total":173,"Min":1,"Max":1},{"Id":33793,"Amount":173,"Pct":0.5,"Total":173,"Min":1,"Max":1}]},"All":{"Total":4495,"Items":[{"Id":33795,"Amount":2242,"Pct":0.498776,"Total":2242,"Min":1,"Max":1},{"Id":33793,"Amount":2253,"Pct":0.501224,"Total":2253,"Min":1,"Max":1}]}}},{"Id":33779,"Name":"Forgotten Fragment of Cunning","Patches":{"7.1":{"Total":5322,"Items":[{"Id":33795,"Amount":2615,"Pct":0.491357,"Total":2615,"Min":1,"Max":1},{"Id":33794,"Amount":2707,"Pct":0.508643,"Total":2707,"Min":1,"Max":1}]},"7.2":{"Total":671,"Items":[{"Id":33795,"Amount":332,"Pct":0.494784,"Total":332,"Min":1,"Max":1},{"Id":33794,"Amount":339,"Pct":0.505216,"Total":339,"Min":1,"Max":1}]},"7.3":{"Total":382,"Items":[{"Id":33795,"Amount":183,"Pct":0.479058,"Total":183,"Min":1,"Max":1},{"Id":33794,"Amount":199,"Pct":0.520942,"Total":199,"Min":1,"Max":1}]},"All":{"Total":6375,"Items":[{"Id":33795,"Amount":3130,"Pct":0.49098,"Total":3130,"Min":1,"Max":1},{"Id":33794,"Amount":3245,"Pct":0.50902,"Total":3245,"Min":1,"Max":1}]}}}]}]